[
  {
    "title": "키세스x키스x키세스[완결]",
    "img": "//dn-img-page.kakao.com/download/resource?kid=blzNFf/hzHNCngEbX/Cof2kN9ozOvQOGyABrVDu0&filename=th3",
    "url": "https://page.kakao.com/content/50316833",
    "summary": "고등학생인 미정이 친구의 \"키스 줘!\" 발언으로 혼란스러운 청춘 연애를 그린 웹툰 '키세스x키스x키세스'. 매주 토요일 업데이트.",
    "keywords": [
      "고등학생",
      "혼란스러운 청춘 연애",
      "친구의 발언",
      "매주 업데이트"
    ]
  },
  {
    "title": "마침내 푸른 불꽃이",
    "img": "//dn-img-page.kakao.com/download/resource?kid=SGOTi/hzHNvhnkJK/9h48KTsKfio2WQITLSAdw1&filename=th3",
    "url": "https://page.kakao.com/content/52093729",
    "summary": "정명공주가 동생을 잃고 광해군에게 유폐된 경운궁에서 살고 있으며, 상궁 김개시는 그녀를 죽이려 한다. 정명공주는 도깨비의 힘을 빌려 과거로 돌아가고자 한다. 매주 화요일 00시에 연재된다.",
    "keywords": [
      "역사",
      "판타지",
      "로맨스",
      "시대극"
    ]
  },
  {
    "title": "그림자 황비",
    "img": "//dn-img-page.kakao.com/download/resource?kid=b2lgW0/hzHNDmaXSO/6FmhCV5fzeHkQpCPdJlyw1&filename=th3",
    "url": "https://page.kakao.com/content/55309903",
    "summary": "여주인공이 가짜 딸로 교환되어 황비가 되어 황태자의 아들을 낳고, 그때 죽은 줄 알았던 베로니카 공녀가 나타나 인형으로 사는 엘레나는 아이를 빼앗기고 죽임을 당하다 다시 과거로 돌아오고, 복수를 결심하게 된 이야기.",
    "keywords": [
      "여주인공",
      "가짜 딸",
      "복수",
      "황비"
    ]
  },
  {
    "title": "용사의 전 여친입니다",
    "img": "//dn-img-page.kakao.com/download/resource?kid=ca2KmQ/hzHNwN7AaR/DP1k7BcwOkESggxJ24Zm40&filename=th3",
    "url": "https://page.kakao.com/content/55215137",
    "summary": "빙의한 여주인공이 기대했던 인생과는 다른 현실을 맞이하며 용사 남자친구와 이별하고 새로운 사랑을 찾지만 그 사랑의 대상이 마왕인 남편이라는 충격적인 사실이 밝혀진다.",
    "keywords": [
      "빙의",
      "이별",
      "마왕",
      "사랑"
    ]
  },
  {
    "title": "이뤄질 수 없는 마녀의 소망",
    "img": "//dn-img-page.kakao.com/download/resource?kid=7Xfti/hzCs8eVTsm/5NmbWpBCtH76KlvtevEKg1&filename=th3",
    "url": "https://page.kakao.com/content/52960341",
    "summary": "어린 나이에 대화재로 가족과 집을 잃고 고아원에서 힘든 삶을 살던 카이델이 백작부인과 함께 하얀 머리의 소녀를 쫓으며 범인의 단서를 찾는 이야기.",
    "keywords": [
      "마녀",
      "고아",
      "백작부인",
      "살인사건"
    ]
  },
  {
    "title": "도장을 찍어주세요",
    "img": "//dn-img-page.kakao.com/download/resource?kid=bdDWCZ/hzHNCA0t87/EkkAzKu45IxnJV1xQ0jczk&filename=th3",
    "url": "https://page.kakao.com/content/53589714",
    "summary": "자수성가 대표가 된 대학생 지아가 맞선을 거부하고, 같은 과 선배인 연후와 재벌가 손자 승호와 함께 하우스메이트로 살면서 최종 신랑감을 결정하게 된다. 지아가 결혼식 꿈을 꾸면서 운명의 신랑감을 찾는 이야기를 담은 웹툰 <도장을 찍어주세요>.",
    "keywords": [
      "자수성가 대학생",
      "맞선 거부",
      "하우스메이트",
      "최종 신랑감 결정"
    ]
  },
  {
    "title": "남의 BL만화 [BL]",
    "img": "//dn-img-page.kakao.com/download/resource?kid=cNSo15/hzHNCANN0V/2AlYfRKoDmMqPOAc1l3Qq0&filename=th3",
    "url": "https://page.kakao.com/content/48991093",
    "summary": "주인공 승희는 동성애자이며 크로스 드레서로, 자신의 진짜 인연을 찾기 위해 노력하면서 어느 날 남자와 만남을 갖고 실랑이를 벌이고, 박승택에게 목격당하게 된다.",
    "keywords": [
      "BL",
      "동성애",
      "크로스 드레서",
      "목격당함"
    ]
  },
  {
    "title": "양극의 소년",
    "img": "//dn-img-page.kakao.com/download/resource?kid=xQYEM/hzHNEr3ldM/q9Swfw13kJ742bqsYIU78K&filename=th3",
    "url": "https://page.kakao.com/content/52618479",
    "summary": "'알텝 바이러스'가 퍼져서 변이한 사람들이 나오고, 그 중 하나인 고등학생 헤테로 강하루가 ISO 대원을 꿈꾸면서 벌어지는 이야기를 매주 월요일에 연재하는 웹툰이다.",
    "keywords": [
      "양극",
      "알템 바이러스",
      "변이",
      "고등학생"
    ]
  },
  {
    "title": "폭군황제의 첫사랑",
    "img": "//dn-img-page.kakao.com/download/resource?kid=dfjNgm/hzHNAwdBUp/lpubgRfkfOCP7gNYpgUr60&filename=th3",
    "url": "https://page.kakao.com/content/54103714",
    "summary": "기억을 잃은 소녀 디아가 황제 카이르에게 납치되고, 황성에서 생활하게 된다. 하지만 어느 날 성 밖으로 나가 마주치게 된 카이르의 비밀을 알게 된다.",
    "keywords": [
      "폭군황제",
      "납치",
      "기억상실",
      "비밀노출"
    ]
  },
  {
    "title": "응급입니다♥",
    "img": "//dn-img-page.kakao.com/download/resource?kid=cmz21P/hzKkVSu6LH/HOQq27nPqqLah2aRMqHUkk&filename=th3",
    "url": "https://page.kakao.com/content/50133486",
    "summary": "음악대학 졸업생인 소이는 제주에서 취업 준비를 하다가 서울 연성병원에 취직하게 된다. 씩씩하게 자기 소개를 마치고 병원 생활을 시작한 소이는 파란만장한 메디컬 로맨스를 경험하며 성장해간다. 초보 간호사 소이의 응급실 라이프를 그린 이야기다.",
    "keywords": [
      "의대",
      "취업",
      "간호사",
      "메디컬로맨스"
    ]
  },
  {
    "title": "네 살 차이",
    "img": "//dn-img-page.kakao.com/download/resource?kid=bBe7YD/hzHNvIEzbs/dQ4chBNas6nXZpBuxkMdr0&filename=th3",
    "url": "https://page.kakao.com/content/51880599",
    "summary": "이레와 강이 5살 때 엄마들의 약속으로 결혼 약속을 하게 되고, 이후 10여 년 후 다시 만나면서 서로의 궁합과 차이를 극복해가며 짝이 될 수 있는지를 그린 웹툰.",
    "keywords": [
      "연애",
      "나이차",
      "짝사랑",
      "운명"
    ]
  },
  {
    "title": "크로스 더 라인",
    "img": "//dn-img-page.kakao.com/download/resource?kid=t9b6D/hzHNApr1sP/aJlujCSTOVeyzvpk15NbI0&filename=th3",
    "url": "https://page.kakao.com/content/52542743",
    "summary": "12년형 받은 은하연, 조직 상무 지태만 집에 데려가 동거 시작. 두 사람의 돌봄과 작은 빛을 찾는 이야기.",
    "keywords": [
      "크로스더라인",
      "동거",
      "은하연",
      "조직 상무"
    ]
  },
  {
    "title": "가짜 공녀님의 만렙 토끼",
    "img": "//dn-img-page.kakao.com/download/resource?kid=MUCTg/hzHNwacnHm/isJ4smdtdeMveOhWrk4YPK&filename=th3",
    "url": "https://page.kakao.com/content/56501182",
    "summary": "라리사는 가짜 공녀로 제국 사교계에서 시선을 받지만, 그녀의 본명은 라리사이고 이전에는 가난한 집안에서 노점장사를 하며 살았다. 털이 검은 토끼도 가짜이며, 정체는 대륙에서 선망받는 대공이다. 이들의 우연한 만남을 통해 대공은 라리사를 돕게 되고, 점점 그녀의 진실을 알아가며 마음에 품게 된다.",
    "keywords": [
      "가짜 공녀",
      "토끼",
      "대공",
      "진실"
    ]
  },
  {
    "title": "독재",
    "img": "//dn-img-page.kakao.com/download/resource?kid=bheTJQ/hzCthvWOO0/SCXuazgYSVM2G3UL3RNss1&filename=th3",
    "url": "https://page.kakao.com/content/54224754",
    "summary": "남자와 여자가 우연히 만나 사랑을 시작하고, 남자는 술탄의 후계자이다. 이제 그는 여자를 평생 소유하려고 한다. 이 웹툰은 김신형작가의 소설 [독재]을 바탕으로 제작된 것이다.",
    "keywords": [
      "사랑",
      "술탄",
      "평생 소유",
      "소설"
    ]
  },
  {
    "title": "유리의 벽",
    "img": "//dn-img-page.kakao.com/download/resource?kid=cExFTb/hzHNyL9Onf/MrKg78OR6DQVhXPQcjGc20&filename=th3",
    "url": "https://page.kakao.com/content/53770819",
    "summary": "순수하고 착한 릴리아나가 음악교사인 평민 에드워드에게 끌리면서 두 사람 사이의 감정 선이 어긋나며, 릴리의 아버지가 결혼을 강요하는 상황에서 이야기가 전개된다.",
    "keywords": [
      "유리",
      "새로운",
      "사랑",
      "장벽"
    ]
  },
  {
    "title": "붉은 여우",
    "img": "//dn-img-page.kakao.com/download/resource?kid=cuP3N1/hzCtgDNs5x/1uTr0536c6ZsrOtYeQvW6K&filename=th3",
    "url": "https://page.kakao.com/content/53513637",
    "summary": "\"붉은 여우\"는 인간 모습으로 둔갑하여 인간의 간을 빼먹는 무시무시한 요물이며, 만약 만난다면 가진 것을 전부 주거나 자신의 간을 바치도록 한다. 그렇지 않으면 자손이 영겁토록 여우의 저주를 받게 된다. 이야기는 화요일마다 연재된다. 15세 이용가로 수정된 개정판이다.",
    "keywords": [
      "요괴",
      "인간 모습",
      "저주",
      "간 빼먹기"
    ]
  },
  {
    "title": "쇼윈도 커플",
    "img": "//dn-img-page.kakao.com/download/resource?kid=etcIMR/hzHNzddTOQ/TVK8upBDCzmPtxBf62cClk&filename=th3",
    "url": "https://page.kakao.com/content/54375031",
    "summary": "인싸인 사훈과 아싸인 다연의 계약연애 이야기 <쇼윈도 커플>.",
    "keywords": [
      "커플",
      "계약연애",
      "인싸",
      "아싸"
    ]
  },
  {
    "title": "우렁강도",
    "img": "//dn-img-page.kakao.com/download/resource?kid=bnag9n/hzHNE6spn7/KFi2V4Pr3abq58OW3GISAK&filename=th3",
    "url": "https://page.kakao.com/content/53275341",
    "summary": "강도와 함께하는 살벌하고 유쾌한 동거 라이프. 지호는 자취방을 구한 뒤 강도와의 만남을 시작하게 된다.",
    "keywords": [
      "우렁강도",
      "강도",
      "살벌하고 유쾌한",
      "동거 라이프"
    ]
  },
  {
    "title": "그 아가씨의 집사님",
    "img": "//dn-img-page.kakao.com/download/resource?kid=c1Kh65/hzHNyk4KNI/VO22oKnlVXR57PQl07oJM0&filename=th3",
    "url": "https://page.kakao.com/content/55253524",
    "summary": "소설 서브남주의 주식을 산 서우리가 자신의 최애캐가 나타나며 일어나는 이야기. 로또를 탄 후 최애캐의 행복을 최우선으로 생각하게 된 서우리의 이야기.",
    "keywords": [
      "소설",
      "서브남주",
      "로또",
      "최애캐"
    ]
  },
  {
    "title": "나의 마녀",
    "img": "//dn-img-page.kakao.com/download/resource?kid=5nvTf/hzHNvVYPBh/ZAEaAQA5rPeTx6ko3tewYk&filename=th3",
    "url": "https://page.kakao.com/content/48439569",
    "summary": "세 명의 아름다운 소녀들과 그들의 짧은, 강렬한 사랑 이야기를 다루는 웹툰. 마녀의 영원한 삶과 찰나의 사랑도 다룬다.",
    "keywords": [
      "마녀",
      "아름다운",
      "강렬한",
      "사랑 이야기"
    ]
  },
  {
    "title": "시월드 게임 -please save my husband-",
    "img": "//dn-img-page.kakao.com/download/resource?kid=casj5U/hzCtbCH94u/iM1KBtKtnW0QEPanTTUMk1&filename=th3",
    "url": "https://page.kakao.com/content/55693659",
    "summary": "결혼생활에서의 판타지 이야기를 다루는 웹툰. 주인공은 인생의 굴레와 싸우며 결혼생활을 이어나가고, 남편을 지키고 미래를 찾기 위해 노력한다.",
    "keywords": [
      "결혼",
      "생활",
      "판타지",
      "노력"
    ]
  },
  {
    "title": "폭군의 가정교사가 되겠습니다",
    "img": "//dn-img-page.kakao.com/download/resource?kid=LyKjX/hzCtbbDYcg/V3BoAeAJWET1dJealRzsIK&filename=th3",
    "url": "https://page.kakao.com/content/56503801",
    "summary": "레인시스가 색을 보지 못하는 저주에 갇혀, 여주인공을 만나야 벗어날 수 있다. 하지만 여주인공 설정이 끝나지 않은 상황에서 단역으로 빙의하게 된 레인시스는 여주인공을 찾아서 눈을 밝힐 것이다.",
    "keywords": [
      "가정교사",
      "색감",
      "저주",
      "빙의"
    ]
  },
  {
    "title": "키스해주세요",
    "img": "//dn-img-page.kakao.com/download/resource?kid=bSeRgK/hzHNwt05Bs/mnezk42tdj0K6JJaHwP6z1&filename=th3",
    "url": "https://page.kakao.com/content/53457182",
    "summary": "사내 상사들의 행동으로 고통받던 여직원이 회사를 그만둘 결심을 하게 된다. 이때, 공공의 적인 상사가 뜻밖의 제안을 하며 비밀 키스 계약을 맺는데, 그와 사이에서 벌어지는 일을 그린 로맨스 웹툰이다.",
    "keywords": [
      "회사 상사",
      "여직원",
      "키스",
      "비밀 계약"
    ]
  },
  {
    "title": "익애 ~봉황애사~",
    "img": "//dn-img-page.kakao.com/download/resource?kid=mbthH/hzHNu3P9mu/Xg1STkYkKXddQfO4MZPaxk&filename=th3",
    "url": "https://page.kakao.com/content/53868644",
    "summary": "최씨 일가는 딸을 낳아 부귀영화를 이어왔지만, 어느 날 여자아이가 태어나 부귀영화를 잃을까봐 딸을 낳는 것을 금기시한다. 지환은 최씨 일가에서 유일한 여자아이로 태어나 구박을 받으며 살다가 목숨을 위협받아 집을 나온다. 그러던 중 약속을 기다리던 사내가 찾아오면서, 지환과 사내의 이야기가 시작된다. 이야기는 사이다 여주가 활약하는 강렬한 동양 판타지이다.",
    "keywords": [
      "동양",
      "일가",
      "여자아이",
      "판타지"
    ]
  },
  {
    "title": "아가씨 뜻대로",
    "img": "//dn-img-page.kakao.com/download/resource?kid=oXWZY/hzCtdNPa4m/7ktdtP6xLLu2u1GZvXAiQ1&filename=th3",
    "url": "https://page.kakao.com/content/55842267",
    "summary": "현은서가 증조부를 은인으로 삼아 대재벌 금환그룹에 거둬지다. 15년 후, 차 회장이 은서가 자신의 손자 중 한 명과 결혼하기를 원하는데, 그 손자 중 하나는 은서의 오빠 차진하이다. 은서는 속을 알 수 없는 차진하의 말에 고민하게 된다.",
    "keywords": [
      "증조부",
      "대재벌",
      "결혼",
      "고민"
    ]
  },
  {
    "title": "아무것도 하고 싶지 않아",
    "img": "//dn-img-page.kakao.com/download/resource?kid=9HrvD/hzCtacILJ1/Lk4hvqJLLi1LP4fZayvJjK&filename=th3",
    "url": "https://page.kakao.com/content/52622012",
    "summary": "26살의 주인공이 아무것도 하지 않기로 결심하는 이야기.",
    "keywords": [
      "26살",
      "결심",
      "아무것도 하지 않기",
      "이야기"
    ]
  },
  {
    "title": "풍운전신",
    "img": "//dn-img-page.kakao.com/download/resource?kid=bfj665/hzHNwHlYcj/jEzy3c2LAixk97dgeDOOrK&filename=th3",
    "url": "https://page.kakao.com/content/54254274",
    "summary": "사십년간의 전쟁 후 두 번의 전생을 거치며 돌아온 전투의 신 남자의 무림행.",
    "keywords": [
      "전투의 신",
      "무림",
      "전생",
      "풍운전신"
    ]
  },
  {
    "title": "악녀 메이커",
    "img": "//dn-img-page.kakao.com/download/resource?kid=DZo8f/hzCtcIagF9/VP0H0MrRFPcglJBYk21zMk&filename=th3",
    "url": "https://page.kakao.com/content/56291021",
    "summary": "여주인공이 로맨스 판타지 소설에 빙의되며 악녀로 태어나지만, 진짜 악녀가 되면 루프를 멈출 수 있다는 수수께끼의 남자와 만나 악녀로 거듭나기 위한 수업을 받는 이야기.",
    "keywords": [
      "로맨스",
      "판타지",
      "빙의",
      "악녀"
    ]
  },
  {
    "title": "찬란한 액션 유치원",
    "img": "//dn-img-page.kakao.com/download/resource?kid=bzKLFg/hzHNzxwfXw/BqqYbKveVfWeXvlNpf4t61&filename=th3",
    "url": "https://page.kakao.com/content/53956161",
    "summary": "아이들의 우정과 평화를 다룬 유년 드라마.",
    "keywords": [
      "액션",
      "유치원",
      "우정",
      "평화"
    ]
  },
  {
    "title": "폭군 남편이 달라졌어요",
    "img": "//dn-img-page.kakao.com/download/resource?kid=cD978I/hzCtdUQbrg/hZhkDRo3LE3EQ7twkItxIK&filename=th3",
    "url": "https://page.kakao.com/content/55539262",
    "summary": "억지로 폭군 대공과 결혼한 이드리스의 불안한 결혼 생활 그리고 자객에 의해 사망한 후 다시 돌아온 이야기. 하지만 폭군 대공인 칼리드가 갑자기 달라지며 이드리스를 위해 뭐든 하겠다는 말을 건네는 이야기.",
    "keywords": [
      "결혼",
      "불안",
      "자객",
      "달라진"
    ]
  },
  {
    "title": "대군으로 살어리랏다",
    "img": "//dn-img-page.kakao.com/download/resource?kid=eQ9MM/hzHNEZGNrG/SiYpq58ClOIhSTvjJ98OV0&filename=th3",
    "url": "https://page.kakao.com/content/55591955",
    "summary": "전생한 평범한 대한민국 취준생이 조선 대군인 진성대군으로 다시 태어나 폭군으로 알려진 연산군을 성군으로 만들고 부인도 지키기 위해 노력하는 이야기.",
    "keywords": [
      "조선",
      "대군",
      "폭군",
      "부인"
    ]
  },
  {
    "title": "초상화",
    "img": "//dn-img-page.kakao.com/download/resource?kid=c0fhYi/hzHNA4guKY/CMYUg594oHYoawLEnlBSZk&filename=th3",
    "url": "https://page.kakao.com/content/51339274",
    "summary": "18세기 유럽, 화가 클라이튼 백작가문에서 딸의 초상화를 그려달라는데, 그는 제자인 헬리를 보내게 된다.",
    "keywords": [
      "초상화",
      "유럽",
      "화가",
      "제자"
    ]
  },
  {
    "title": "양말도깨비",
    "img": "//dn-img-page.kakao.com/download/resource?kid=q8OiN/hzHNCHLOFz/BhF7lZLPZ6m73w7psqs8Rk&filename=th3",
    "url": "https://page.kakao.com/content/52500124",
    "summary": "도깨비 때문에 양말이 사라지는 이야기. 집에도 도깨비가 있을지 모른다.",
    "keywords": [
      "양말",
      "도깨비",
      "사라지는",
      "집"
    ]
  },
  {
    "title": "천인의 신부",
    "img": "//dn-img-page.kakao.com/download/resource?kid=z9qf9/hzCtgjIgwC/0lVpiaUKP1XFSLKHWvDiP0&filename=th3",
    "url": "https://page.kakao.com/content/55705058",
    "summary": "총비인 채연은 천인의 신부가 되어 운명을 바꾸기로 결심하고 사당으로 향하다가 고 귀비의 병사들에게 쫓기지만, 날개를 단 남자가 나타나 구해준 후, 천인과의 계약 혼인으로 인생이 바뀌는 이야기를 다룬 웹툰이다.",
    "keywords": [
      "천인",
      "신부",
      "운명",
      "계약 혼인"
    ]
  },
  {
    "title": "레이디 생존의 법칙",
    "img": "//dn-img-page.kakao.com/download/resource?kid=cdLlai/hzCtfEVkKe/xqkKEh5y2MoBO04Tz06Nwk&filename=th3",
    "url": "https://page.kakao.com/content/55387088",
    "summary": "여자 주인공이 네 번의 환생 후 다섯 번째 빙의를 통해 블루 스크린 삶을 벗어나 결국 속아 넘어가는 이야기를 담은 웹툰.",
    "keywords": [
      "\"여주 네 번 환생",
      "블루스크린",
      "결국 속아넘김\""
    ]
  },
  {
    "title": "악당에게 사랑을 강요받고 있습니다",
    "img": "//dn-img-page.kakao.com/download/resource?kid=bmi2v0/hzHNzqKveX/2Hglxp0KybkFj1qSgrVWVk&filename=th3",
    "url": "https://page.kakao.com/content/55136850",
    "summary": "시골에 살던 세니야에게 악명 높은 공작이 무릎 꿇고 청혼하며 그녀와 결혼하도록 강요한다. 이제 세니야는 이 공작과의 결혼을 피할 수 없게 된다. 이것이 <악당에게 사랑을 강요 받고 있습니다>라는 웹툰의 내용이다.",
    "keywords": [
      "악당",
      "사랑 강요",
      "결혼",
      "시골 소녀"
    ]
  },
  {
    "title": "거부할 수 없는 운명",
    "img": "//dn-img-page.kakao.com/download/resource?kid=bwd3cp/hzHNC8P2CP/8mk3Qw5miow0C5oq8Ss621&filename=th3",
    "url": "https://page.kakao.com/content/54343727",
    "summary": "병약한 오라비를 위해 자신을 감추고 사는 자하국의 공주 자설란은 부마간섭을 벗어나기 위해 최지환과 결혼하려고 하지만, 최지환은 괴물이라는 저주에 사로잡힌 채 혼사를 거부한다. 하지만, 그들이 직면한 참혹한 진실은 저주보다 더 심각한 것이었다. 이야기는 기적과 운명으로 이루어진 제작 메이드 인 코리아 웹툰이다.",
    "keywords": [
      "공주",
      "결혼",
      "괴물",
      "운명"
    ]
  },
  {
    "title": "이별을 희망합니다",
    "img": "//dn-img-page.kakao.com/download/resource?kid=Ei7sd/hzCs9Sd2Yn/C7mmSdvvcLIoNzNLJ0Ptx1&filename=th3",
    "url": "https://page.kakao.com/content/54889995",
    "summary": "악녀에게 빙의한 여주인공이 살인당하는 위험에서 벗어나기 위해 세 남자와 이별하고 살아남기 위해 노력하는 이야기. 윤여음 작가의 \"이별을 희망합니다\" 웹툰화.",
    "keywords": [
      "악녀",
      "살인",
      "세 남자",
      "노력"
    ]
  },
  {
    "title": "하트 크러시",
    "img": "//dn-img-page.kakao.com/download/resource?kid=cOZ4tj/hzHNFEu8nF/PPpI7igbA40U9s8GkK4zb1&filename=th3",
    "url": "https://page.kakao.com/content/57045506",
    "summary": "웹툰은 한국 대학 흉부외과 2년 차 레지던트인 유다온이 교수님에게 고백하고 그 후 벌어지는 일들을 그린 러브 서바이벌 이야기이다.",
    "keywords": [
      "대학",
      "흉부외과",
      "러브서바이벌",
      "고백"
    ]
  },
  {
    "title": "스머프 월드",
    "img": "//dn-img-page.kakao.com/download/resource?kid=bbOPuG/hzMT5L90Oo/R6ykKQuAoryz8umkgh4lkk&filename=th3",
    "url": "https://page.kakao.com/content/53856587",
    "summary": "재벌 후계자가 돈세탁업자를 납치하고 탈제호를 시도하며, 시즌 2에서 새로운 커플이 등장하여 로맨틱 무드에 휩싸이는 이야기. 15세 이용가.",
    "keywords": [
      "스머프",
      "후계자",
      "돈세탁",
      "로맨틱"
    ]
  },
  {
    "title": "묵향 디 오리진",
    "img": "//dn-img-page.kakao.com/download/resource?kid=c5GWx/hzHNuW4x2R/KZDcbMf0PwpWXGYuEISFTK&filename=th3",
    "url": "https://page.kakao.com/content/56458652",
    "summary": "전동조 장편 소설 [묵향]의 초대형 웹툰 프로젝트 [묵향 디 오리진]으로, 무림 정점에 오르는 암살자 묵향의 이야기를 다룬다. 수많은 고수와의 격돌과 궁극의 무를 좇는 묵향의 전설적인 일대기를 그린다. 이어지는 2부는 [묵향 다크레이디]에서 볼 수 있다.",
    "keywords": [
      "무림",
      "암살자",
      "고수",
      "전설적인"
    ]
  },
  {
    "title": "욕망이라는 것에 대하여",
    "img": "//dn-img-page.kakao.com/download/resource?kid=vAMNr/hzCs8zfxPj/8NS9J8BlvKUxmuGsUJkkek&filename=th3",
    "url": "https://page.kakao.com/content/53201510",
    "summary": "웹툰은 \"성애\"와 \"순애\"의 마음을 지닌 두 쌍의 인물들 간의 연애 이야기를 다루고 있다. 또한, 김재희와 강범철의 쌍방삽질 티격태격 배틀연애도 함께 다루고 있다. 성인을 위한 작품으로, 매주 목요일에 연재되고 있다.",
    "keywords": [
      "성애",
      "순애",
      "삽질",
      "연애"
    ]
  },
  {
    "title": "침묵의 정원",
    "img": "//dn-img-page.kakao.com/download/resource?kid=bt440T/hzCtgYlhRH/dPI8io4WqtFYEUu1K6Vt41&filename=th3",
    "url": "https://page.kakao.com/content/56868082",
    "summary": "이 웹툰은 헌신적으로 가족을 돌보던 여자가 남편과 딸의 죽음으로 인해 내면의 세계가 뒤틀리고 새로운 삶을 시작하는 이야기이다.",
    "keywords": [
      "헌신",
      "가족",
      "죽음",
      "새로운 삶"
    ]
  },
  {
    "title": "호형호제",
    "img": "//dn-img-page.kakao.com/download/resource?kid=cpCb2u/hzCtawPTr0/NMWqkZcYGzBkHdELnFyGfk&filename=th3",
    "url": "https://page.kakao.com/content/53168421",
    "summary": "'상화'는 오랜 친구인 '려한'을 짝사랑하면서도 질투하며, 뉴비 '이금'을 만나 游戏를 하고, 결국 미스터리한 남자 '최강미래'와 만나 호형호제하던 사람이 조폭 같은 남자라는 충격을 받는 이야기다.",
    "keywords": [
      "호형호제",
      "짝사랑",
      "미스터리",
      "조폭"
    ]
  },
  {
    "title": "그 알파를 꼬시는 법 [BL]",
    "img": "//dn-img-page.kakao.com/download/resource?kid=cVF0ld/hzHNxsI7jt/mn0KwOh2tRngm1k4VBqVWk&filename=th3",
    "url": "https://page.kakao.com/content/53731361",
    "summary": "부잣집 막내아들인 윤우영은 외모, 재력, 학벌 등 모든 면에서 완벽하지만 열성 오메가라는 특이체질 때문에 약한 자신을 컴플렉스로 삼고 있다. 그러나 우성 알파 차경주와의 원나잇 이후, 윤우영의 몸에 이상한 변화가 일어나는데...",
    "keywords": [
      "부잣집",
      "막내아들",
      "오메가",
      "알파"
    ]
  },
  {
    "title": "황녀의 생존법칙",
    "img": "//dn-img-page.kakao.com/download/resource?kid=cRCoOV/hzHNv9v25j/TcD5KmmGKMgCn8kW4PGtnk&filename=th3",
    "url": "https://page.kakao.com/content/55453259",
    "summary": "신선들이 사는 선경에서 자신이 사랑한 사내와 결혼한 능소파 선녀 청아는 남편에게 금단을 빼앗기고 죽음을 맞이한다. 하지만 태어나자마자 아레스 제국의 황녀로 환생해 '버림 받은 황녀', '불길한 아이', '제물'로 저주받은 쌍둥이에게 영혼을 바치게 된다. 이제 사야는 비운의 황녀로서 잘 살아갈 수 있을까?",
    "keywords": [
      "황녀",
      "환생",
      "저주",
      "쌍둥이"
    ]
  },
  {
    "title": "신마",
    "img": "//dn-img-page.kakao.com/download/resource?kid=bsJLDw/hzCtbibEjM/OwQqmFr8MZtxTjfCgj4kxk&filename=th3",
    "url": "https://page.kakao.com/content/57474947",
    "summary": "공전절후의 풍운아가 신과 마력을 지닌 전쟁에서 활약하는 이야기. 마교 교주가 환생 프로젝트로 다시 살아난 후 뚱보 공자로 환생해 전 무림을 향해 전쟁을 선언한다.",
    "keywords": [
      "신마",
      "전쟁",
      "마력",
      "환생"
    ]
  },
  {
    "title": "결혼하고 합시다",
    "img": "//dn-img-page.kakao.com/download/resource?kid=9UJwD/hzHNzRB4dj/X5QL44g6T4t4xtvrJSiqF1&filename=th3",
    "url": "https://page.kakao.com/content/57500275",
    "summary": "모아는 결혼은 싫어하는 비혼주의자인데, 상사 건후의 완벽한 몸매에 광선을 받게 되고 고민하던 중 폭탄 고백을 하게 된다. 하지만 건후는 결혼할 여자가 아니면 안 한다고 대답한다.",
    "keywords": [
      "비혼주의자",
      "완벽한 몸매",
      "폭탄 고백",
      "결혼할 여자만"
    ]
  },
  {
    "title": "펌킨타임",
    "img": "//dn-img-page.kakao.com/download/resource?kid=byNhH7/hzHNvWaWsX/o3KyoZRtwVtivmREOaXBY1&filename=th3",
    "url": "https://page.kakao.com/content/53764621",
    "summary": "'신해원'은 자신의 성별이 남자에서 여자로 바뀌었지만 친구 '강태주'에게 말하지 못하고 헤어지게 된 후, 몇 년 뒤 '태주'가 돌아와 해원을 찾으면서 어느 여고생과의 관계도 복잡해진다.",
    "keywords": [
      "성변환",
      "비밀",
      "재회",
      "복잡한 관계"
    ]
  },
  {
    "title": "거짓말, 뱀파이어가 어디 있어? [BL]",
    "img": "//dn-img-page.kakao.com/download/resource?kid=btX6QI/hzMT8oxXcS/1x65AFnPSccFEv7CKyxjrK&filename=th3",
    "url": "https://page.kakao.com/content/53437762",
    "summary": "'도시로 가라'는 동하가 아빠의 유언에 따라 도시로 내려와 첫 하우스메이트로 뱀파이어 친구들과 함께 생활하는 이야기이다. 이들은 동하의 해맑음에 마음을 빼앗기고 결국 동하의 피를 마시게 된다.",
    "keywords": [
      "도시",
      "하우스메이트",
      "뱀파이어",
      "흡혈"
    ]
  }
]